detectDashCam/__init__.py
detectDashCam/detectDashCam.py
detectDashCam-0.0.3.dist-info/METADATA
detectDashCam-0.0.3.dist-info/RECORD
detectDashCam-0.0.3.dist-info/WHEEL
detectDashCam-0.0.3.dist-info/top_level.txt
